{
  "ticker": "AAPL",
  "company_name": "Apple Inc.",
  "cik": "0000320193",
  "record": {
    "accession_number": "0001193125-17-064019",
    "filing_date": "2017-03-01",
    "report_date": "2017-02-28",
    "acceptance_datetime": "2017-03-01T14:00:56.000Z",
    "act": "34",
    "form": "8-K",
    "file_number": "001-36743",
    "film_number": "17651574",
    "items": "5.07",
    "size": 49026,
    "is_xbrl": 0,
    "is_inline_xbrl": 0,
    "primary_document": "d342218d8k.htm",
    "primary_doc_description": "FORM 8-K"
  },
  "urls": {
    "directory_index_json": "https://www.sec.gov/Archives/edgar/data/320193/000119312517064019/index.json",
    "full_submission_txt": "https://www.sec.gov/Archives/edgar/data/320193/000119312517064019/0001193125-17-064019.txt",
    "primary_document": "https://www.sec.gov/Archives/edgar/data/320193/000119312517064019/d342218d8k.htm"
  },
  "synced_at_utc": "2026-03-27T10:50:15.933515+00:00"
}
